{"scoutName":"Erin Okada","teamNum":"4619","matchType":"Qualification","matchNum":"4","currentStatus":"Functional","startPosition":"Null","startLevel":"1","crossLine":false,"playstyle":"Scoring","totalRocketHatch":"00","totalRocketCargo":"02","totalCargoshipHatch":"00","totalCargoshipCargo":"02","highestRocket":"0","highestCargo":"Level 1","groundHatch":false,"groundCargo":false,"climbTime":"Choose...","climbLevel":"No Climb","climbAssist":false,"assistedClimb":false,"SRocketHatch":"0","SRocketCargo":"0","SCargoshipHatch":"0","SCargoshipCargo":"0","TRocketHatch":"0","TRocketCargo":"2","TCargoshipHatch":"0","TCargoshipCargo":"2","SComment":"lost pre load ball","TComment":"","EComment":""}