{"scoutName":"Erin Okada","teamNum":"3473","matchType":"Qualification","matchNum":"52","currentStatus":"Functional","startLevel":"2","playstyle":"Scoring","totalRocketHatch":"00","totalRocketCargo":"00","totalCargoshipHatch":"11","totalCargoshipCargo":"04","highestRocket":"","highestCargo":"Choose...","groundHatch":false,"groundCargo":true,"climbTime":"Choose...","climbLevel":"Choose...","climbAssist":false,"assistedClimb":false,"SRocketHatch":"0","SRocketCargo":"0","SCargoshipHatch":"1","SCargoshipCargo":"0","TRocketHatch":"0","TRocketCargo":"0","TCargoshipHatch":"1","TCargoshipCargo":"4","SComment":"","TComment":"super fast and good at cargo and hatch panels","EComment":"tried l2 climb but couldn't get up in time due to misalignment, overall really good, would be a good pick"}